pyjpi/__init__.py
pyjpi/library.py
pyjpi-0.1.26.dist-info/licenses/LICENSE
pyjpi-0.1.26.dist-info/METADATA
pyjpi-0.1.26.dist-info/WHEEL
pyjpi-0.1.26.dist-info/top_level.txt
pyjpi-0.1.26.dist-info/RECORD
