Metadata-Version: 2.4
Name: pyJPI
Version: 0.1.26
Summary: A library to access Android devices which run JPI
Author-email: Pierre Wieser <p.wieser@trychlos.org>
License-Expression: MIT
Project-URL: Homepage, https://github.com/trychlos/pyjpi
Project-URL: Issues, https://github.com/trychlos/pyjpi/issues
Classifier: Programming Language :: Python :: 3
Classifier: Operating System :: OS Independent
Requires-Python: >=3.10
License-File: LICENSE
Dynamic: license-file
